djangoldp_resource/__init__.py
djangoldp_resource/admin.py
djangoldp_resource/apps.py
djangoldp_resource/factories.py
djangoldp_resource/models.py
djangoldp_resource/views.py
djangoldp_resource/migrations/0001_initial.py
djangoldp_resource/migrations/0002_auto_20200426_1902.py
djangoldp_resource/migrations/0002_resource_user.py
djangoldp_resource/migrations/0003_auto_20200616_0957.py
djangoldp_resource/migrations/0003_resource_conversations.py
djangoldp_resource/migrations/0004_merge_20200616_1011.py
djangoldp_resource/migrations/0005_merge_20200616_1030.py
djangoldp_resource/migrations/0006_auto_20200617_1458.py
djangoldp_resource/migrations/0007_auto_20200709_1411.py
djangoldp_resource/migrations/0008_auto_20200812_1446.py
djangoldp_resource/migrations/0009_auto_20200812_1459.py
djangoldp_resource/migrations/0010_auto_20200923_1017.py
djangoldp_resource/migrations/0011_auto_20210525_1018.py
djangoldp_resource/migrations/0012_auto_20210525_1022.py
djangoldp_resource/migrations/0013_auto_20221012_1503.py
djangoldp_resource/migrations/0014_auto_20221027_0958.py
djangoldp_resource/migrations/0015_alter_keyword_options_alter_resource_options_and_more.py
djangoldp_resource/migrations/0016_keyword_created_at_keyword_updated_at_and_more.py
djangoldp_resource/migrations/__init__.py
djangoldp_resource-5.0.0.dist-info/METADATA
djangoldp_resource-5.0.0.dist-info/WHEEL
djangoldp_resource-5.0.0.dist-info/top_level.txt
djangoldp_resource-5.0.0.dist-info/RECORD
